whisperer_ml/__init__.py
whisperer_ml/auto_labeler.py
whisperer_ml/config/__init__.py
whisperer_ml/config/config.py
whisperer_ml/converter.py
whisperer_ml/diarizer.py
whisperer_ml/main.py
whisperer_ml/paths/__init__.py
whisperer_ml/paths/dataset.py
whisperer_ml/paths/default.py
whisperer_ml/paths/speaker.py
whisperer_ml/transcriber.py
whisperer_ml/utils/__init__.py
whisperer_ml/utils/utils.py
whisperer_ml-0.1.7.dist-info/METADATA
whisperer_ml-0.1.7.dist-info/WHEEL
whisperer_ml-0.1.7.dist-info/entry_points.txt
whisperer_ml-0.1.7.dist-info/RECORD
