Metadata-Version: 2.1
Name: whisperer-ml
Version: 0.1.7
Summary: Go from raw audio to a text-audio dataset with OpenAI's Whisper
Author: miguelvalente
Author-email: miguelvalente@protonmail.com
Requires-Python: >=3.9,<3.11
Classifier: Programming Language :: Python :: 3
Classifier: Programming Language :: Python :: 3.9
Classifier: Programming Language :: Python :: 3.10
Requires-Dist: ffmpeg-python (>=0.2.0,<0.3.0)
Requires-Dist: jupyter (>=1.0.0,<2.0.0)
Requires-Dist: librosa (==0.8.0)
Requires-Dist: numpy (==1.22.3)
Requires-Dist: openai-whisper (>=20230124,<20230125)
Requires-Dist: pyannote-audio (>=2.1.1,<3.0.0)
Requires-Dist: pydub (==0.25.1)
Requires-Dist: scipy (==1.8.0)
Requires-Dist: torch (==1.13.0)
Requires-Dist: torchaudio (==0.13.0)
Requires-Dist: tqdm (>=4.64.1,<5.0.0)
Requires-Dist: transformers (>=4.25.1,<5.0.0)
Requires-Dist: typer (>=0.7.0,<0.8.0)
